.testr.conf
AUTHORS
ChangeLog
HACKING.rst
LICENSE
README.rst
babel.cfg
openstack-common.conf
requirements.txt
setup.cfg
setup.py
test-requirements.txt
tox.ini
doc/source/conf.py
doc/source/index.rst
python_ripcordclient.egg-info/PKG-INFO
python_ripcordclient.egg-info/SOURCES.txt
python_ripcordclient.egg-info/dependency_links.txt
python_ripcordclient.egg-info/entry_points.txt
python_ripcordclient.egg-info/requires.txt
python_ripcordclient.egg-info/top_level.txt
ripcordclient/__init__.py
ripcordclient/client.py
ripcordclient/test.py
ripcordclient/version.py
ripcordclient/cmd/__init__.py
ripcordclient/cmd/shell.py
ripcordclient/common/__init__.py
ripcordclient/common/base.py
ripcordclient/common/exception.py
ripcordclient/common/http.py
ripcordclient/common/utils.py
ripcordclient/openstack/__init__.py
ripcordclient/openstack/common/__init__.py
ripcordclient/openstack/common/gettextutils.py
ripcordclient/openstack/common/importutils.py
ripcordclient/openstack/common/jsonutils.py
ripcordclient/openstack/common/local.py
ripcordclient/openstack/common/log.py
ripcordclient/openstack/common/strutils.py
ripcordclient/openstack/common/timeutils.py
ripcordclient/shell/__init__.py
ripcordclient/shell/v1/__init__.py
ripcordclient/shell/v1/base.py
ripcordclient/shell/v1/subscriber.py
ripcordclient/tests/__init__.py
ripcordclient/tests/utils.py
ripcordclient/tests/v1/__init__.py
ripcordclient/tests/v1/test_subscriber.py
ripcordclient/v1/__init__.py
ripcordclient/v1/client.py
ripcordclient/v1/subscriber.py