Metadata-Version: 1.1
Name: python-ripcordclient
Version: 0.0.1
Summary: Client library for Ripcord API
Home-page: UNKNOWN
Author: Paul Belanger
Author-email: paul.belanger@polybeacon.com
License: Apache-2
Platform: UNKNOWN
Classifier: Development Status :: 3 - Alpha
Classifier: Environment :: Console
Classifier: Intended Audience :: Information Technology
Classifier: Intended Audience :: System Administrators
Classifier: License :: OSI Approved :: Apache Software License
Classifier: Operating System :: OS Independent
Classifier: Programming Language :: Python
